AUTHORS.rst
LICENSE
MANIFEST.in
README.rst
setup.py
doc/CHANGELOG.rst
doc/Makefile
doc/conf.py
doc/imports.rst
doc/index.rst
doc/install.rst
doc/make.bat
doc/userguide.rst
examples/rmi.py
examples/jms/README.TXT
examples/jms/testJpypePublisher.py
examples/jms/testJpypeSubscriber.py
examples/linux/README.TXT
examples/linux/findjvm.py
examples/linux/jpype.sh
ha_JPype1.egg-info/PKG-INFO
ha_JPype1.egg-info/SOURCES.txt
ha_JPype1.egg-info/dependency_links.txt
ha_JPype1.egg-info/not-zip-safe
ha_JPype1.egg-info/requires.txt
ha_JPype1.egg-info/top_level.txt
jpype/JClassUtil.py
jpype/__init__.py
jpype/_classpath.py
jpype/_core.py
jpype/_cygwin.py
jpype/_darwin.py
jpype/_gui.py
jpype/_jarray.py
jpype/_jboxed.py
jpype/_jclass.py
jpype/_jcollection.py
jpype/_jexception.py
jpype/_jio.py
jpype/_jobject.py
jpype/_jpackage.py
jpype/_jproxy.py
jpype/_jvmfinder.py
jpype/_jwrapper.py
jpype/_linux.py
jpype/_properties.py
jpype/_pykeywords.py
jpype/_refdaemon.py
jpype/_windows.py
jpype/imports.py
jpype/nio.py
jpype/reflect.py
jpype/awt/__init__.py
jpype/awt/event/WindowAdapter.py
jpype/awt/event/__init__.py
jpypex/__init__.py
jpypex/swing/AbstractAction.py
jpypex/swing/__init__.py
jpypex/swing/pyutils.py
native/build.xml
native/common/jp_array.cpp
native/common/jp_arrayclass.cpp
native/common/jp_booleantype.cpp
native/common/jp_bytetype.cpp
native/common/jp_chartype.cpp
native/common/jp_class.cpp
native/common/jp_classbase.cpp
native/common/jp_cleaner.cpp
native/common/jp_doubletype.cpp
native/common/jp_env.cpp
native/common/jp_field.cpp
native/common/jp_floattype.cpp
native/common/jp_hostref.cpp
native/common/jp_inttype.cpp
native/common/jp_jcharstring.cpp
native/common/jp_jniutil.cpp
native/common/jp_longtype.cpp
native/common/jp_method.cpp
native/common/jp_methodoverload.cpp
native/common/jp_monitor.cpp
native/common/jp_object.cpp
native/common/jp_objecttype.cpp
native/common/jp_platform_linux.cpp
native/common/jp_platform_win32.cpp
native/common/jp_proxy.cpp
native/common/jp_reference_queue.cpp
native/common/jp_shorttype.cpp
native/common/jp_stringtype.cpp
native/common/jp_tracer.cpp
native/common/jp_typemanager.cpp
native/common/jp_typename.cpp
native/common/jp_voidtype.cpp
