Metadata-Version: 2.1
Name: ha-JPype1
Version: 2.6.6
Summary: A Python to Java bridge.
Home-page: https://github.com/originell/jpype/
Author: Steve Menard
Author-email: devilwolf@users.sourceforge.net
Maintainer: Luis Nell
Maintainer-email: cooperate@originell.org
License: License :: OSI Approved :: Apache Software License
Platform: Operating System :: MacOS :: MacOS X
Platform: Operating System :: Microsoft :: Windows :: Windows 7
Platform: Operating System :: Microsoft :: Windows :: Windows Vista
Platform: Operating System :: POSIX :: Linux
Classifier: Programming Language :: Java
Classifier: Programming Language :: Python :: 2.6
Classifier: Programming Language :: Python :: 2.7
Classifier: Programming Language :: Python :: 3
Classifier: Programming Language :: Python :: 3.5
Classifier: Programming Language :: Python :: 3.6
Provides-Extra: numpy
